Workbook

Sheet 1. Modelo y TOP
B2: INVESTIGACIÓN OPERATIVA - UTN
B3: Unidad 6: Programación Lineal Continua - Ejercicio 1a (Modelo Base)
B5: 1. ENUNCIADO
B6: 1a.- Cada planta fabrica envases de yogures (x1) y de bebidas (x2). Los envases se venden a $8 y $6 respectivamente. Por mes solo se pueden usar 600 hs máquina y 800 kg de material reciclado. Para fabricar yogures se requieren 2 hs máquina y 4 kg de material reciclado. Para fabricar bebidas se requieren 3 hs máquina y 2 kg de material reciclado. Objetivo: Hallar el mix óptimo de producción en forma analítica para obtener la mayor ganancia posible.
B9: 2. FORMULACIÓN DEL MODELO PRIMAL
B10: Elemento | C10: Notación | D10: x1 (Yogur) | E10: x2 (Bebida) | F10: Relación | G10: Disponibilidad | H10: Unidad
B11: Funcional | C11: Max Z | D11: 8 | E11: 6 | F11: = | G11: - | H11: $/unidad
B12: Restricción 1 | C12: Hs Máquina | D12: 2 | E12: 3 | F12: <= | G12: 600 | H12: horas/mes
B13: Restricción 2 | C13: Material Reciclado | D13: 4 | E13: 2 | F13: <= | G13: 800 | H13: kg/mes
B14: Cond. No Negatividad | C14: x1, x2 | D14: >= 0 | E14: >= 0 | F14: - | G14: - | H14: -
B16: 3. TABLA ÓPTIMA DEL PRIMAL (TOP)
B17: Se resuelve analíticamente saturando ambas restricciones (sistema 2x2: 2·x1 + 3·x2 = 600 y 4·x1 + 2·x2 = 800):
E18: =D11 -> 8 | F18: =E11 -> 6 | G18: 0 | H18: 0
B19: Ck | C19: Xk | D19: Bk | E19: x1 | F19: x2 | G19: λ1 (hs) | H19: λ2 (mat)
B20: =D11 -> 8 | C20: x1 | D20: =G20*G12+H20*G13 -> 150 | E20: 1 | F20: 0 | G20: {=MINVERSE(D12:E13)} -> -0.25 | H20: 0.375
B21: =E11 -> 6 | C21: x2 | D21: =G21*G12+H21*G13 -> 100 | E21: 0 | F21: 1 | G21: 0.5 | H21: -0.25
B22: Z | C22: = | D22: =B20*D20+B21*D21 -> 1800
B23: zj - cj | C23: = | E23: =B20*E20+B21*E21-E18 -> 0 | F23: =B20*F20+B21*F21-F18 -> 0 | G23: =B20*G20+B21*G21-G18 -> 1 | H23: =B20*H20+B21*H21-H18 -> 1.5
B25: 4. LECTURA DE RESULTADOS DEL MODELO BASE
B26: Mix óptimo de producción: | C26: ="x1* = " & TEXT(D20,"#,##0") & " envases de yogur | x2* = " & TEXT(D21,"#,##0") & " envases de bebida" -> x1* = 150 envases de yogur | x2* = 100 envases de bebida
B27: Ganancia Máxima (Z*): | C27: =TEXT(D22,"\$#,##0.00") & " por mes" -> $1,800.00 por mes
B28: Uso de recursos: | C28: 600 hs máquina utilizadas (100%) | 800 kg de material utilizados (100%) -> λ1 = 0, λ2 = 0
B29: Valor Marginal Hs Máquina (y1): | C29: ="$" & TEXT(G23,"#,##0.00") & " por cada hora adicional de máquina (columna λ1 en fila zj-cj)" -> $1.00 por cada hora adicional de máquina (columna λ1 en fila zj-cj)
B30: Valor Marginal Material (y2): | C30: ="$" & TEXT(H23,"#,##0.00") & " por cada kg adicional de material reciclado (columna λ2 en fila zj-cj)" -> $1.50 por cada kg adicional de material reciclado (columna λ2 en fila zj-cj)

Sheet 2. Analisis Post-Optimo (P3)
B2: INVESTIGACIÓN OPERATIVA - UTN
B3: Unidad 6: Análisis Post-Óptimo - Evaluación de un Nuevo Producto (Inciso 1b)
B5: ¿POR QUÉ NO SE VUELVE A RESOLVER POR SIMPLEX?
B6: REGLA DE LA CÁTEDRA: En la práctica profesional y en los exámenes de IO, NUNCA se rehace Simplex desde cero cuando se evalúa incorporar un nuevo producto. Se utiliza la información ya obtenida en la Tabla Óptima del Primal (TOP). Un nuevo producto solo se producirá si su margen de ganancia supera lo que 'cuesta' utilizar los recursos que consume (valorizados a sus valores marginales / precios sombra). Esto se evalúa con el LUCRO CESANTE (zj) y el COSTO DE OPORTUNIDAD (cj - zj).
B10: 1. DATOS DEL NUEVO PRODUCTO (x3: Envases de Postre)
B11: Parámetro | C11: Símbolo | D11: Valor | E11: Unidad | F11: Descripción
B12: Consumo Hs Máquina | C12: a13 | D12: 1 | E12: hs/unidad | F12: Horas máquina necesarias por cada envase de postre
B13: Consumo Material Reciclado | C13: a23 | D13: 2 | E13: kg/unidad | F13: Kg de material reciclado requeridos por envase
B14: Precio de Venta propuesto (Caso 1) | C14: c3 | D14: 3.5 | E14: $/unidad | F14: Precio de mercado a evaluar
B15: Precio de Venta alternativo (Caso 2) | C15: c3' | D15: 5 | E15: $/unidad | F15: Escenario con precio más alto
B17: 2. CÁLCULO ANALÍTICO: LUCRO CESANTE (z3)
B18: Lucro Cesante = Σ (Valor Marginal_i × Requerimiento_i) --> Valor de los recursos que consume el producto 3
B19: Recurso i | C19: Valor Marginal (yi) | D19: Consumo de x3 (ai3) | E19: Aporte al Lucro Cesante ($) | F19: Fórmula
B20: Hs Máquina (Recurso 1) | C20: ='1. Modelo y TOP'!G23 -> 1 | D20: 1 | E20: =C20*D20 -> 1 | F20: y1 · a13 = $1,00/h × 1 h
B21: Material Reciclado (Recurso 2) | C21: ='1. Modelo y TOP'!H23 -> 1.5 | D21: 2 | E21: =C21*D21 -> 3 | F21: y2 · a23 = $1,50/kg × 2 kg
B22: LUCRO CESANTE TOTAL (z3) | E22: =SUM(E20:E21) -> 4 | F22: z3 = $1,00 + $3,00 = $4,00
B24: 3. EVALUACIÓN DEL COSTO DE OPORTUNIDAD (z3 - c3)
B25: Escenario | C25: Precio de Venta (c3) | D25: Lucro Cesante (z3) | E25: Costo de Oportunidad (c3 - z3) | F25: ¿Conviene Fabricar? | G25: Conclusión Pedagógica
B26: Caso 1: Precio = $3,50 | C26: =D14 -> 3.5 | D26: =E22 -> 4 | E26: =C26-D26 -> -0.5 | F26: =IF(E26>0,"SÍ CONVIENE","NO CONVIENE") -> NO CONVIENE | G26: ="c3 - z3 = " & TEXT(E26,"+0.00;-0.00;0.00") & IF(E26>0," > 0. Conviene producirlo (entraría a la base de Simplex mejorando Z).",IF(E26<0," < 0. El producto pierde " & TEXT(-E26,"$#,##0.00") & " frente a las alternativas. x3 queda en 0."," = 0. Cero alternativo. No altera la ganancia total óptima.")) -> c3 - z3 = -0.50 < 0. El producto pierde $0.50 frente a las alternativas. x3 queda en 0.
B27: Caso 2: Precio = $5,00 | C27: =D15 -> 5 | D27: =E22 -> 4 | E27: =C27-D27 -> 1 | F27: =IF(E27>0,"SÍ CONVIENE","NO CONVIENE") -> SÍ CONVIENE | G27: ="c3 - z3 = " & TEXT(E27,"+0.00;-0.00;0.00") & IF(E27>0," > 0. Conviene producirlo (entraría a la base de Simplex mejorando Z).",IF(E27<0," < 0. El producto pierde " & TEXT(-E27,"$#,##0.00") & " frente a las alternativas. x3 queda en 0."," = 0. Cero alternativo. No altera la ganancia total óptima.")) -> c3 - z3 = +1.00 > 0. Conviene producirlo (entraría a la base de Simplex mejorando Z).
B28: Punto de Indiferencia | C28: =E22 -> 4 | D28: =E22 -> 4 | E28: =C28-D28 -> 0 | F28: =IF(E28>0,"SÍ CONVIENE",IF(E28<0,"NO CONVIENE","INDIFERENTE")) -> INDIFERENTE | G28: ="c3 - z3 = " & TEXT(E28,"+0.00;-0.00;0.00") & IF(E28>0," > 0. Conviene producirlo (entraría a la base de Simplex mejorando Z).",IF(E28<0," < 0. El producto pierde " & TEXT(-E28,"$#,##0.00") & " frente a las alternativas. x3 queda en 0."," = 0. Cero alternativo. No altera la ganancia total óptima.")) -> c3 - z3 = 0.00 = 0. Cero alternativo. No altera la ganancia total óptima.
B31: 4. TABLA DE SENSIBILIDAD DEL PRECIO DEL NUEVO PRODUCTO
B32: Sensibilidad de la decisión según el precio de venta c3:
B33: Precio c3 ($) | C33: Lucro Cesante z3 ($) | D33: Costo Oportunidad (c3 - z3) | E33: Criterio de Decisión | F33: Impacto en el Plan de Producción
B34: 2 | C34: =$E$22 -> 4 | D34: =B34-C34 -> -2 | E34: =IF(D34>0,"FABRICAR",IF(D34<0,"NO FABRICAR","INDIFERENTE")) -> NO FABRICAR | F34: =IF(E34="NO FABRICAR","x3 = 0 (Se mantiene mix original: " & TEXT('1. Modelo y TOP'!D20,"#,##0") & " yogures, " & TEXT('1. Modelo y TOP'!D21,"#,##0") & " bebidas, Z=" & TEXT('1. Modelo y TOP'!D22,"\$#,##0.00") & ")",IF(E34="INDIFERENTE","Solución múltiple (0 alternativo): no varía Z=" & TEXT('1. Modelo y TOP'!D22,"\$#,##0.00"),"x3 entra a la base: desplaza unidades de x1 y aumenta Z > " & TEXT('1. Modelo y TOP'!D22,"\$#,##0.00"))) -> x3 = 0 (Se mantiene mix original: 150 yogures, 100 bebidas, Z=$1,800.00)
B35: 2.5 | C35: =$E$22 -> 4 | D35: =B35-C35 -> -1.5 | E35: =IF(D35>0,"FABRICAR",IF(D35<0,"NO FABRICAR","INDIFERENTE")) -> NO FABRICAR | F35: =IF(E35="NO FABRICAR","x3 = 0 (Se mantiene mix original: " & TEXT('1. Modelo y TOP'!D20,"#,##0") & " yogures, " & TEXT('1. Modelo y TOP'!D21,"#,##0") & " bebidas, Z=" & TEXT('1. Modelo y TOP'!D22,"\$#,##0.00") & ")",IF(E35="INDIFERENTE","Solución múltiple (0 alternativo): no varía Z=" & TEXT('1. Modelo y TOP'!D22,"\$#,##0.00"),"x3 entra a la base: desplaza unidades de x1 y aumenta Z > " & TEXT('1. Modelo y TOP'!D22,"\$#,##0.00"))) -> x3 = 0 (Se mantiene mix original: 150 yogures, 100 bebidas, Z=$1,800.00)
B36: 3 | C36: =$E$22 -> 4 | D36: =B36-C36 -> -1 | E36: =IF(D36>0,"FABRICAR",IF(D36<0,"NO FABRICAR","INDIFERENTE")) -> NO FABRICAR | F36: =IF(E36="NO FABRICAR","x3 = 0 (Se mantiene mix original: " & TEXT('1. Modelo y TOP'!D20,"#,##0") & " yogures, " & TEXT('1. Modelo y TOP'!D21,"#,##0") & " bebidas, Z=" & TEXT('1. Modelo y TOP'!D22,"\$#,##0.00") & ")",IF(E36="INDIFERENTE","Solución múltiple (0 alternativo): no varía Z=" & TEXT('1. Modelo y TOP'!D22,"\$#,##0.00"),"x3 entra a la base: desplaza unidades de x1 y aumenta Z > " & TEXT('1. Modelo y TOP'!D22,"\$#,##0.00"))) -> x3 = 0 (Se mantiene mix original: 150 yogures, 100 bebidas, Z=$1,800.00)
B37: 3.5 | C37: =$E$22 -> 4 | D37: =B37-C37 -> -0.5 | E37: =IF(D37>0,"FABRICAR",IF(D37<0,"NO FABRICAR","INDIFERENTE")) -> NO FABRICAR | F37: =IF(E37="NO FABRICAR","x3 = 0 (Se mantiene mix original: " & TEXT('1. Modelo y TOP'!D20,"#,##0") & " yogures, " & TEXT('1. Modelo y TOP'!D21,"#,##0") & " bebidas, Z=" & TEXT('1. Modelo y TOP'!D22,"\$#,##0.00") & ")",IF(E37="INDIFERENTE","Solución múltiple (0 alternativo): no varía Z=" & TEXT('1. Modelo y TOP'!D22,"\$#,##0.00"),"x3 entra a la base: desplaza unidades de x1 y aumenta Z > " & TEXT('1. Modelo y TOP'!D22,"\$#,##0.00"))) -> x3 = 0 (Se mantiene mix original: 150 yogures, 100 bebidas, Z=$1,800.00)
B38: 4 | C38: =$E$22 -> 4 | D38: =B38-C38 -> 0 | E38: =IF(D38>0,"FABRICAR",IF(D38<0,"NO FABRICAR","INDIFERENTE")) -> INDIFERENTE | F38: =IF(E38="NO FABRICAR","x3 = 0 (Se mantiene mix original: " & TEXT('1. Modelo y TOP'!D20,"#,##0") & " yogures, " & TEXT('1. Modelo y TOP'!D21,"#,##0") & " bebidas, Z=" & TEXT('1. Modelo y TOP'!D22,"\$#,##0.00") & ")",IF(E38="INDIFERENTE","Solución múltiple (0 alternativo): no varía Z=" & TEXT('1. Modelo y TOP'!D22,"\$#,##0.00"),"x3 entra a la base: desplaza unidades de x1 y aumenta Z > " & TEXT('1. Modelo y TOP'!D22,"\$#,##0.00"))) -> Solución múltiple (0 alternativo): no varía Z=$1,800.00
B39: 4.5 | C39: =$E$22 -> 4 | D39: =B39-C39 -> 0.5 | E39: =IF(D39>0,"FABRICAR",IF(D39<0,"NO FABRICAR","INDIFERENTE")) -> FABRICAR | F39: =IF(E39="NO FABRICAR","x3 = 0 (Se mantiene mix original: " & TEXT('1. Modelo y TOP'!D20,"#,##0") & " yogures, " & TEXT('1. Modelo y TOP'!D21,"#,##0") & " bebidas, Z=" & TEXT('1. Modelo y TOP'!D22,"\$#,##0.00") & ")",IF(E39="INDIFERENTE","Solución múltiple (0 alternativo): no varía Z=" & TEXT('1. Modelo y TOP'!D22,"\$#,##0.00"),"x3 entra a la base: desplaza unidades de x1 y aumenta Z > " & TEXT('1. Modelo y TOP'!D22,"\$#,##0.00"))) -> x3 entra a la base: desplaza unidades de x1 y aumenta Z > $1,800.00
B40: 5 | C40: =$E$22 -> 4 | D40: =B40-C40 -> 1 | E40: =IF(D40>0,"FABRICAR",IF(D40<0,"NO FABRICAR","INDIFERENTE")) -> FABRICAR | F40: =IF(E40="NO FABRICAR","x3 = 0 (Se mantiene mix original: " & TEXT('1. Modelo y TOP'!D20,"#,##0") & " yogures, " & TEXT('1. Modelo y TOP'!D21,"#,##0") & " bebidas, Z=" & TEXT('1. Modelo y TOP'!D22,"\$#,##0.00") & ")",IF(E40="INDIFERENTE","Solución múltiple (0 alternativo): no varía Z=" & TEXT('1. Modelo y TOP'!D22,"\$#,##0.00"),"x3 entra a la base: desplaza unidades de x1 y aumenta Z > " & TEXT('1. Modelo y TOP'!D22,"\$#,##0.00"))) -> x3 entra a la base: desplaza unidades de x1 y aumenta Z > $1,800.00
B41: 5.5 | C41: =$E$22 -> 4 | D41: =B41-C41 -> 1.5 | E41: =IF(D41>0,"FABRICAR",IF(D41<0,"NO FABRICAR","INDIFERENTE")) -> FABRICAR | F41: =IF(E41="NO FABRICAR","x3 = 0 (Se mantiene mix original: " & TEXT('1. Modelo y TOP'!D20,"#,##0") & " yogures, " & TEXT('1. Modelo y TOP'!D21,"#,##0") & " bebidas, Z=" & TEXT('1. Modelo y TOP'!D22,"\$#,##0.00") & ")",IF(E41="INDIFERENTE","Solución múltiple (0 alternativo): no varía Z=" & TEXT('1. Modelo y TOP'!D22,"\$#,##0.00"),"x3 entra a la base: desplaza unidades de x1 y aumenta Z > " & TEXT('1. Modelo y TOP'!D22,"\$#,##0.00"))) -> x3 entra a la base: desplaza unidades de x1 y aumenta Z > $1,800.00
B42: 6 | C42: =$E$22 -> 4 | D42: =B42-C42 -> 2 | E42: =IF(D42>0,"FABRICAR",IF(D42<0,"NO FABRICAR","INDIFERENTE")) -> FABRICAR | F42: =IF(E42="NO FABRICAR","x3 = 0 (Se mantiene mix original: " & TEXT('1. Modelo y TOP'!D20,"#,##0") & " yogures, " & TEXT('1. Modelo y TOP'!D21,"#,##0") & " bebidas, Z=" & TEXT('1. Modelo y TOP'!D22,"\$#,##0.00") & ")",IF(E42="INDIFERENTE","Solución múltiple (0 alternativo): no varía Z=" & TEXT('1. Modelo y TOP'!D22,"\$#,##0.00"),"x3 entra a la base: desplaza unidades de x1 y aumenta Z > " & TEXT('1. Modelo y TOP'!D22,"\$#,##0.00"))) -> x3 entra a la base: desplaza unidades de x1 y aumenta Z > $1,800.00
B45: 5. COLUMNA GENERADA EN EL TABLEAU (Tasa de Sustitución)
B46: ="Si el producto 3 ingresara a la base (ej. a $" & TEXT(D15,"#,##0.00") & "), ¿a qué productos desplaza?" & CHAR(10) & "Se calcula con la matriz inversa B^-1 de la TOP multiplicada por los consumos A3:" & CHAR(10) & "Y3 = B^-1 · A3 = [[ " & TEXT('1. Modelo y TOP'!G20,"0.000") & ", " & TEXT('1. Modelo y TOP'!H20,"0.000") & " ], [ " & TEXT('1. Modelo y TOP'!G21,"0.000") & ", " & TEXT('1. Modelo y TOP'!H21,"0.000") & " ]] · [ " & TEXT(D12,"#,##0") & ", " & TEXT(D13,"#,##0") & " ]^T = [ " & TEXT('1. Modelo y TOP'!G20*D12+'1. Modelo y TOP'!H20*D13,"0.00") & ", " & TEXT('1. Modelo y TOP'!G21*D12+'1. Modelo y TOP'!H21*D13,"0.00") & " ]^T" & CHAR(10) & "Interpretación: Por cada envase de postre (x3) que se fabrique, se debe reducir " & TEXT('1. Modelo y TOP'!G20*D12+'1. Modelo y TOP'!H20*D13,"#,##0.0") & " envases de yogur (x1) y " & TEXT('1. Modelo y TOP'!G21*D12+'1. Modelo y TOP'!H21*D13,"#,##0.0") & " envases de bebida (x2). ¡Tampoco requiere rehacer la tabla entera!" -> Si el producto 3 ingresara a la base (ej. a $5.00), ¿a qué productos desplaza? Se calcula con la matriz inversa B^-1 de la TOP multiplicada por los consumos A3: Y3 = B^-1 · A3 = [[ -0.250, 0.375 ], [ 0.500, -0.250 ]] · [ 1, 2 ]^T = [ 0.50, 0.00 ]^T Interpretación: Por cada envase de postre (x3) que se fabrique, se debe reducir 0.5 envases de yogur (x1) y 0.0 envases de bebida (x2). ¡Tampoco requiere rehacer la tabla entera!
